langchain_nvidia_trt/__init__.py
langchain_nvidia_trt/llms.py
langchain_nvidia_trt/py.typed
langchain_nvidia_trt-0.0.1rc0.dist-info/LICENSE
langchain_nvidia_trt-0.0.1rc0.dist-info/METADATA
langchain_nvidia_trt-0.0.1rc0.dist-info/WHEEL
langchain_nvidia_trt-0.0.1rc0.dist-info/RECORD
